global_object_factory/__init__.py
global_object_factory/interfaces.py
global_object_factory/object_factory.py
global_object_factory-1.0.1.dist-info/licenses/LICENSE.md
global_object_factory-1.0.1.dist-info/METADATA
global_object_factory-1.0.1.dist-info/WHEEL
global_object_factory-1.0.1.dist-info/top_level.txt
global_object_factory-1.0.1.dist-info/RECORD
