Metadata-Version: 2.4
Name: global-object-factory
Version: 1.0.1
Summary: Global Object Factory for Python - Lightweight dependency injection for legacy code
Author-email: Ivett Ördög <contact@ivettordog.com>
License: # PolyForm Noncommercial License 1.0.0
Project-URL: Homepage, https://github.com/ivettordog/global-object-factory
Project-URL: Repository, https://github.com/ivettordog/global-object-factory
Project-URL: Documentation, https://github.com/ivettordog/global-object-factory
Classifier: Development Status :: 4 - Beta
Classifier: Intended Audience :: Developers
Classifier: Programming Language :: Python :: 3
Classifier: Programming Language :: Python :: 3.8
Classifier: Programming Language :: Python :: 3.9
Classifier: Programming Language :: Python :: 3.10
Classifier: Programming Language :: Python :: 3.11
Classifier: Programming Language :: Python :: 3.12
Requires-Python: >=3.8
License-File: LICENSE.md
Provides-Extra: test
Requires-Dist: pytest>=7.0.0; extra == "test"
Requires-Dist: pytest-cov>=4.0.0; extra == "test"
Provides-Extra: dev
Requires-Dist: mypy>=1.0.0; extra == "dev"
Requires-Dist: black>=22.0.0; extra == "dev"
Requires-Dist: isort>=5.0.0; extra == "dev"
Requires-Dist: pytest>=7.0.0; extra == "dev"
Requires-Dist: pytest-cov>=4.0.0; extra == "dev"
Dynamic: license-file
